opendatacrawler/CkanCrawler.py
opendatacrawler/INECrawler.py
opendatacrawler/OpenDataSoftCrawler.py
opendatacrawler/SocrataCrawler.py
opendatacrawler/ZenodoCrawler.py
opendatacrawler/__init__.py
opendatacrawler/__main__.py
opendatacrawler/datosgobescrawler.py
opendatacrawler/eurostatcrawler.py
opendatacrawler/intro.txt
opendatacrawler/odcrawler.py
opendatacrawler/opendatacrawlerInterface.py
opendatacrawler/setup_logger.py
opendatacrawler/utils.py
opendatacrawler/worldbankcrawler.py
opendatacrawler-1.0.17.dist-info/LICENSE
opendatacrawler-1.0.17.dist-info/METADATA
opendatacrawler-1.0.17.dist-info/WHEEL
opendatacrawler-1.0.17.dist-info/entry_points.txt
opendatacrawler-1.0.17.dist-info/top_level.txt
opendatacrawler-1.0.17.dist-info/RECORD
