Metadata-Version: 2.1
Name: opendatacrawler
Version: 1.0.17
Summary: Crawler for open data portals
Home-page: https://github.com/aberenguerpas/OpenDataCrawler/
Author: Alberto Berenguer Pastor
Author-email: alberto.berenguer@ua.es
License: MIT
Classifier: License :: OSI Approved :: MIT License
Classifier: Programming Language :: Python :: 3
Classifier: Programming Language :: Python :: 3.9
License-File: LICENSE
Requires-Dist: tqdm
Requires-Dist: sodapy
